vulcan_annotation/__init__.py
vulcan_annotation/annotation.py
vulcan_annotation/utilities.py
vulcan_annotation/js/va_dom.js
vulcan_annotation/js/vulcan_annotation.js
vulcan_annotation-3.1.6.dist-info/LICENSE
vulcan_annotation-3.1.6.dist-info/METADATA
vulcan_annotation-3.1.6.dist-info/WHEEL
vulcan_annotation-3.1.6.dist-info/top_level.txt
vulcan_annotation-3.1.6.dist-info/RECORD
