Metadata-Version: 2.1
Name: vulcan-annotation
Version: 3.1.6
Summary: Vulcan annotation for structured data.
Home-page: https://github.com/vulcan-coalition/vulcan_annotation
Author: Chatavut Viriyasuthee
Author-email: chatavut@lab.ai
Classifier: Programming Language :: Python :: 3
Classifier: License :: OSI Approved :: Apache Software License
Classifier: Operating System :: OS Independent
Requires-Python: >=3.9
License-File: LICENSE
Requires-Dist: shortuuid
Requires-Dist: levenshtein
